denoc/__init__.py
denoc/__main__.py
denoc/core.py
denoc/utils.py
license.md
denoc-1.2.0.dist-info/entry_points.txt
denoc-1.2.0.dist-info/WHEEL
denoc-1.2.0.dist-info/METADATA
denoc-1.2.0.dist-info/RECORD
