Metadata-Version: 2.1
Name: denoc
Version: 1.2.0
Summary: Utilities for compile JavaScript with Deno
Home-page: https://github.com/UltiRequiem/denoc
License: MIT
Keywords: commands,typescript,deno,javascript
Author: Eliaz Bobadilla
Author-email: eliaz.bobadilladev@gmail.com
Requires-Python: >=3.8,<4.0
Classifier: License :: OSI Approved :: MIT License
Classifier: Programming Language :: Python :: 3
Classifier: Programming Language :: Python :: 3.10
Classifier: Programming Language :: Python :: 3.8
Classifier: Programming Language :: Python :: 3.9
Requires-Dist: colores (>=0.1.2,<0.2.0)
Project-URL: Repository, https://github.com/UltiRequiem/denoc
